{
  "_class": "shapeGroup",
  "booleanOperation": 0,
  "clippingMaskMode": 0,
  "do_objectID": "3FFEF979-1D77-4422-A518-5F35C8B1C060",
  "exportOptions": {
    "_class": "exportOptions",
    "do_objectID": "625A48BF-88BB-438B-B795-0C24F608A45D",
    "exportFormats": [
    ],
    "includedLayerIds": [
    ],
    "layerOptions": 0,
    "shouldTrim": false
  },
  "frame": {
    "_class": "rect",
    "constrainProportions": true,
    "do_objectID": "0FBD18F3-1366-4637-B9FF-542A07A41E02",
    "height": 20,
    "width": 20,
    "x": 2,
    "y": 2
  },
  "hasClickThrough": false,
  "hasClippingMask": true,
  "isFixedToViewport": false,
  "isFlippedHorizontal": false,
  "isFlippedVertical": false,
  "isLocked": false,
  "isVisible": true,
  "layerListExpandedType": 0,
  "layers": [
    {
      "class": "shapePath",
      "id": "33EB6D20-EA8D-4F63-99E8-566E72637C05"
    },
    {
      "class": "shapePath",
      "id": "FA3E8629-49DD-4264-8E7F-FEBE857210AB"
    },
    {
      "class": "shapePath",
      "id": "D377FA8C-329C-4484-BF54-459EE9A97D0E"
    },
    {
      "class": "shapePath",
      "id": "9C66AA2E-846B-4CF3-B61C-4C3A16A8B57E"
    },
    {
      "class": "shapePath",
      "id": "C34C3026-6864-43F9-9B89-90BA34770D1D"
    },
    {
      "class": "shapePath",
      "id": "6C9421D9-F44F-483C-B1BC-B97526CF35BC"
    },
    {
      "class": "shapePath",
      "id": "E0DAFE73-4635-489D-A77D-D1E231F32FD9"
    },
    {
      "class": "shapePath",
      "id": "3C6EA761-AD3C-459A-921D-DB7DE103D4B1"
    },
    {
      "class": "shapePath",
      "id": "5EBCE2B1-64CA-4B7E-8E4B-900784264F80"
    },
    {
      "class": "shapePath",
      "id": "84A24141-54AB-4462-827E-1A5D9461E4CC"
    },
    {
      "class": "shapePath",
      "id": "CBB07F06-FFE2-454E-A769-0D8107DCB80B"
    },
    {
      "class": "shapePath",
      "id": "7193351F-63A1-4386-927E-D4E5072F0638"
    },
    {
      "class": "shapePath",
      "id": "0D26111D-C1E5-4F97-812B-BA4E311175D8"
    },
    {
      "class": "shapePath",
      "id": "62F29026-F11B-46C0-AEF0-22983205060C"
    }
  ],
  "name": "icon/image/blur_circular_24px",
  "nameIsFixed": false,
  "resizingConstraint": 63,
  "resizingType": 0,
  "rotation": 0,
  "shouldBreakMaskChain": false,
  "style": {
    "_class": "style",
    "do_objectID": "9CC94199-03A1-4401-8436-CBD9A2E85248",
    "endMarkerType": 0,
    "fills": [
      {
        "_class": "fill",
        "color": {
          "_class": "color",
          "alpha": 1,
          "blue": 0,
          "green": 0,
          "red": 0
        },
        "fillType": 0,
        "isEnabled": false,
        "noiseIndex": 0,
        "noiseIntensity": 0,
        "patternFillType": 1,
        "patternTileScale": 1
      }
    ],
    "miterLimit": 10,
    "startMarkerType": 0,
    "windingRule": 0
  },
  "windingRule": 0
}