{
  "_class": "symbolInstance",
  "booleanOperation": 0,
  "clippingMaskMode": 0,
  "do_objectID": "E93D3616-DD2F-4CB9-BC22-F0C36ED131BE",
  "exportOptions": {
    "_class": "exportOptions",
    "do_objectID": "742AA2D6-6F73-4727-9DA7-E26787DDC3E1",
    "exportFormats": [
    ],
    "includedLayerIds": [
    ],
    "layerOptions": 0,
    "shouldTrim": false
  },
  "frame": {
    "_class": "rect",
    "constrainProportions": false,
    "do_objectID": "47747B1D-D22A-4E95-841E-C4AD30C4455F",
    "height": 101,
    "width": 101,
    "x": 0,
    "y": 0
  },
  "hasClippingMask": false,
  "horizontalSpacing": 0,
  "isFixedToViewport": false,
  "isFlippedHorizontal": false,
  "isFlippedVertical": false,
  "isLocked": false,
  "isVisible": true,
  "layerListExpandedType": 0,
  "name": "↳ Color",
  "nameIsFixed": false,
  "overrideValues": [
  ],
  "resizingConstraint": 63,
  "resizingType": 0,
  "rotation": 0,
  "scale": 1,
  "shouldBreakMaskChain": false,
  "style": {
    "_class": "style",
    "do_objectID": "946B23E3-5AF2-4EFE-9EE4-C93215A40796",
    "endMarkerType": 0,
    "miterLimit": 10,
    "startMarkerType": 0,
    "windingRule": 1
  },
  "symbolID": "DB70345C-9C90-4C24-8B5F-D9D150918674",
  "verticalSpacing": 0
}