{
  "_class": "shapeGroup",
  "booleanOperation": 0,
  "clippingMaskMode": 0,
  "do_objectID": "7FB945B2-1300-4786-A102-B6E56ECBCCD8",
  "exportOptions": {
    "_class": "exportOptions",
    "do_objectID": "A60A217E-8302-4D5C-9046-19648C33CEBF",
    "exportFormats": [
    ],
    "includedLayerIds": [
    ],
    "layerOptions": 0,
    "shouldTrim": false
  },
  "frame": {
    "_class": "rect",
    "constrainProportions": false,
    "do_objectID": "55EAD50A-1EA4-4006-AA71-C89FFA54EFAA",
    "height": 18,
    "width": 18,
    "x": 3,
    "y": 3
  },
  "hasClickThrough": false,
  "hasClippingMask": true,
  "isFixedToViewport": false,
  "isFlippedHorizontal": false,
  "isFlippedVertical": false,
  "isLocked": false,
  "isVisible": true,
  "layerListExpandedType": 1,
  "layers": [
    {
      "class": "shapePath",
      "id": "993E9F90-B845-48C2-B398-5866C0E81573"
    },
    {
      "class": "shapePath",
      "id": "E8D6CF7E-87E1-454C-BD1E-3496D7505559"
    },
    {
      "class": "shapePath",
      "id": "7D9FF906-6507-47D3-A479-A96C5C5C8074"
    }
  ],
  "name": "icon/content/move_to_inbox_24px",
  "nameIsFixed": false,
  "resizingConstraint": 63,
  "resizingType": 0,
  "rotation": 0,
  "shouldBreakMaskChain": false,
  "style": {
    "_class": "style",
    "do_objectID": "E769CC78-E142-4755-A304-239BE47BD14E",
    "endMarkerType": 0,
    "fills": [
      {
        "_class": "fill",
        "color": {
          "_class": "color",
          "alpha": 1,
          "blue": 0,
          "green": 0,
          "red": 0
        },
        "fillType": 0,
        "isEnabled": false,
        "noiseIndex": 0,
        "noiseIntensity": 0,
        "patternFillType": 1,
        "patternTileScale": 1
      }
    ],
    "miterLimit": 10,
    "startMarkerType": 0,
    "windingRule": 0
  },
  "windingRule": 0
}