{
  "_class": "symbolMaster",
  "backgroundColor": {
    "_class": "color",
    "alpha": 1,
    "blue": 1,
    "do_objectID": "53A7D4F4-BA0F-4CD6-B786-4778A7A08BCB",
    "green": 1,
    "red": 1
  },
  "booleanOperation": 0,
  "changeIdentifier": 118,
  "clippingMaskMode": 0,
  "do_objectID": "87275DB2-6FAC-4C7E-88A4-102CD97CAE3A",
  "exportOptions": {
    "_class": "exportOptions",
    "do_objectID": "E1AA0B2D-79C3-41E6-93EE-54E4559BA927",
    "exportFormats": [
      {
        "_class": "exportFormat",
        "absoluteSize": 0,
        "fileFormat": "svg",
        "name": "_two_tone",
        "namingScheme": 0,
        "scale": 1,
        "visibleScaleType": 0
      }
    ],
    "includedLayerIds": [
    ],
    "layerOptions": 0,
    "shouldTrim": false
  },
  "frame": {
    "_class": "rect",
    "constrainProportions": false,
    "do_objectID": "18CA36FA-A122-4A97-BC71-DEC3636AA274",
    "height": 24,
    "width": 24,
    "x": 1467,
    "y": 808
  },
  "hasBackgroundColor": false,
  "hasClickThrough": true,
  "hasClippingMask": false,
  "horizontalRulerData": {
    "_class": "rulerData",
    "base": 0,
    "do_objectID": "5489E1FF-FEA0-4109-A81B-E577472791C7",
    "guides": [
    ]
  },
  "includeBackgroundColorInExport": true,
  "includeBackgroundColorInInstance": true,
  "includeInCloudUpload": true,
  "isFixedToViewport": false,
  "isFlippedHorizontal": false,
  "isFlippedVertical": false,
  "isFlowHome": false,
  "isLocked": false,
  "isVisible": true,
  "layerListExpandedType": 2,
  "layers": [
    {
      "class": "group",
      "id": "5D6975B4-8ADE-4C3A-98B2-AB6083C7B794"
    },
    {
      "class": "group",
      "id": "1F3D82C4-C2A4-4327-80B6-884B5D012535"
    },
    {
      "class": "group",
      "id": "9BEE26CE-822A-4F84-9314-2BF6C25D3479"
    }
  ],
  "name": "icon/maps/local_activity_24px",
  "nameIsFixed": false,
  "resizesContent": false,
  "resizingConstraint": 63,
  "resizingType": 0,
  "rotation": 0,
  "shouldBreakMaskChain": true,
  "style": {
    "_class": "style",
    "do_objectID": "CF4A1F47-B24E-424A-B29F-EBD5BA773FF6",
    "endMarkerType": 0,
    "miterLimit": 10,
    "startMarkerType": 0,
    "windingRule": 1
  },
  "symbolID": "AB9AFA2F-1FB4-4F60-9367-0F7CB6F49E9A",
  "userInfo": {
    "com.amoreaux.sketch-icons": {
      "padding": 0
    },
    "com.google.ux.material.spec_tools": {
      "iconStyle": "TWO_TONE",
      "symbolName": "icon/maps/local_activity_24px",
      "type": "icon"
    }
  },
  "verticalRulerData": {
    "_class": "rulerData",
    "base": 0,
    "do_objectID": "CBC8204E-1E52-4F9C-8A81-2BB3750DC9E6",
    "guides": [
    ]
  }
}