{
  "_class": "symbolInstance",
  "booleanOperation": 0,
  "clippingMaskMode": 0,
  "do_objectID": "BC82820C-901B-44BA-A371-577B1F1A2A5D",
  "exportOptions": {
    "_class": "exportOptions",
    "do_objectID": "2EE7B590-6221-45EA-BF97-8EE6DAB800D4",
    "exportFormats": [
    ],
    "includedLayerIds": [
    ],
    "layerOptions": 0,
    "shouldTrim": false
  },
  "frame": {
    "_class": "rect",
    "constrainProportions": false,
    "do_objectID": "4C022E42-AB6A-495E-A015-35689B2D5EDA",
    "height": 101,
    "width": 101,
    "x": 0,
    "y": 0
  },
  "hasClippingMask": false,
  "horizontalSpacing": 0,
  "isFixedToViewport": false,
  "isFlippedHorizontal": false,
  "isFlippedVertical": false,
  "isLocked": false,
  "isVisible": true,
  "layerListExpandedType": 0,
  "name": "↳ Color",
  "nameIsFixed": false,
  "overrideValues": [
  ],
  "resizingConstraint": 63,
  "resizingType": 0,
  "rotation": 0,
  "scale": 1,
  "shouldBreakMaskChain": false,
  "style": {
    "_class": "style",
    "do_objectID": "8C4E2156-1DFB-4B53-85EA-AB4F7D3C5F0B",
    "endMarkerType": 0,
    "miterLimit": 10,
    "startMarkerType": 0,
    "windingRule": 1
  },
  "symbolID": "00328DF5-7CC7-446D-9361-E47B5729B092",
  "verticalSpacing": 0
}