{
  "_class": "group",
  "booleanOperation": 0,
  "clippingMaskMode": 0,
  "do_objectID": "8C98856A-BE47-470F-BBD7-771CD45CBFF0",
  "exportOptions": {
    "_class": "exportOptions",
    "do_objectID": "DDFEA3E2-E40E-45CB-99C0-7AF3614F8776",
    "exportFormats": [
    ],
    "includedLayerIds": [
    ],
    "layerOptions": 0,
    "shouldTrim": false
  },
  "frame": {
    "_class": "rect",
    "constrainProportions": false,
    "do_objectID": "38BA3DC4-1FFB-4015-BAF5-11CF7D0AF203",
    "height": 12,
    "width": 22,
    "x": 1,
    "y": 6
  },
  "hasClickThrough": false,
  "hasClippingMask": false,
  "isFixedToViewport": false,
  "isFlippedHorizontal": false,
  "isFlippedVertical": false,
  "isLocked": false,
  "isVisible": true,
  "layerListExpandedType": 0,
  "layers": [
    {
      "class": "shapeGroup",
      "id": "55A13EFE-5C2C-4860-AA51-C86DDDF5B70B"
    },
    {
      "class": "symbolInstance",
      "id": "631FE807-A3EF-464B-88D8-39CED91E3078"
    }
  ],
  "name": "↳ Dark Color",
  "nameIsFixed": false,
  "resizingConstraint": 63,
  "resizingType": 0,
  "rotation": 0,
  "shouldBreakMaskChain": false,
  "style": {
    "_class": "style",
    "do_objectID": "A861AF72-C542-44A7-8588-85323292F89F",
    "endMarkerType": 0,
    "miterLimit": 10,
    "startMarkerType": 0,
    "windingRule": 1
  }
}