{
  "_class": "shapeGroup",
  "booleanOperation": 0,
  "clippingMaskMode": 0,
  "do_objectID": "494F4A99-D9D7-43A1-A5B4-1A32F7B2B7D5",
  "exportOptions": {
    "_class": "exportOptions",
    "do_objectID": "13F35D50-C72A-45CD-8A13-FE26AA790AA8",
    "exportFormats": [
    ],
    "includedLayerIds": [
    ],
    "layerOptions": 0,
    "shouldTrim": false
  },
  "frame": {
    "_class": "rect",
    "constrainProportions": true,
    "do_objectID": "25BB7E3E-D44C-4E90-9D59-0D8D4EDFB56A",
    "height": 14,
    "width": 11,
    "x": 6.5,
    "y": 5
  },
  "hasClickThrough": false,
  "hasClippingMask": true,
  "isFixedToViewport": false,
  "isFlippedHorizontal": false,
  "isFlippedVertical": false,
  "isLocked": false,
  "isVisible": true,
  "layerListExpandedType": 0,
  "layers": [
    {
      "class": "shapePath",
      "id": "F4C06234-AFBD-44BB-BF30-B4E0EF8714B9"
    },
    {
      "class": "shapePath",
      "id": "21CE1F58-238F-4EA0-B56F-28CF50DEBB43"
    }
  ],
  "name": "icon/av/play_arrow_24px",
  "nameIsFixed": false,
  "resizingConstraint": 63,
  "resizingType": 0,
  "rotation": 0,
  "shouldBreakMaskChain": false,
  "style": {
    "_class": "style",
    "do_objectID": "09961741-392A-4674-89AA-79E62DC6C8C7",
    "endMarkerType": 0,
    "fills": [
      {
        "_class": "fill",
        "color": {
          "_class": "color",
          "alpha": 1,
          "blue": 0,
          "green": 0,
          "red": 0
        },
        "fillType": 0,
        "isEnabled": false,
        "noiseIndex": 0,
        "noiseIntensity": 0,
        "patternFillType": 1,
        "patternTileScale": 1
      }
    ],
    "miterLimit": 10,
    "startMarkerType": 0,
    "windingRule": 0
  },
  "windingRule": 0
}