{
  "_class": "symbolMaster",
  "backgroundColor": {
    "_class": "color",
    "alpha": 1,
    "blue": 1,
    "do_objectID": "B6E1042D-0D8B-4AC1-9204-1DA373DADF99",
    "green": 1,
    "red": 1
  },
  "booleanOperation": 0,
  "changeIdentifier": 411,
  "clippingMaskMode": 0,
  "do_objectID": "7966934B-766A-4133-A159-C1965EBFF402",
  "exportOptions": {
    "_class": "exportOptions",
    "do_objectID": "CF65251B-EFD8-4517-AE3B-AE8B9E2EBE98",
    "exportFormats": [
    ],
    "includedLayerIds": [
    ],
    "layerOptions": 0,
    "shouldTrim": false
  },
  "frame": {
    "_class": "rect",
    "constrainProportions": false,
    "do_objectID": "EF2F06E8-95F9-4D51-BAB8-A0B22100F01E",
    "height": 24,
    "width": 24,
    "x": 1323,
    "y": 757
  },
  "hasBackgroundColor": false,
  "hasClickThrough": true,
  "hasClippingMask": false,
  "horizontalRulerData": {
    "_class": "rulerData",
    "base": 0,
    "do_objectID": "B72D8417-F7F5-492F-A2D7-4DA411BF4EBF",
    "guides": [
    ]
  },
  "includeBackgroundColorInExport": true,
  "includeBackgroundColorInInstance": true,
  "includeInCloudUpload": true,
  "isFixedToViewport": false,
  "isFlippedHorizontal": false,
  "isFlippedVertical": false,
  "isFlowHome": false,
  "isLocked": false,
  "isVisible": true,
  "layerListExpandedType": 0,
  "layers": [
    {
      "class": "shapeGroup",
      "id": "97E498B4-7BE1-46E6-86FA-B12CA8B7DA4F"
    },
    {
      "class": "symbolInstance",
      "id": "5810FCAA-D418-4F36-BF89-63A09CE7235F"
    }
  ],
  "name": "icon/maps/directions_railway_24px",
  "nameIsFixed": false,
  "resizesContent": false,
  "resizingConstraint": 63,
  "resizingType": 0,
  "rotation": 0,
  "shouldBreakMaskChain": true,
  "style": {
    "_class": "style",
    "do_objectID": "25D8F672-4AD5-459C-92F8-3CFB7FD36F88",
    "endMarkerType": 0,
    "miterLimit": 10,
    "startMarkerType": 0,
    "windingRule": 1
  },
  "symbolID": "D5429F0B-8C98-476E-B3BB-AEF913B815A3",
  "userInfo": {
    "com.amoreaux.sketch-icons": {
      "color": "51DBFA7F-7275-4C51-AD4E-19143533FEE4",
      "colorLib": "EA9A3456-D205-45BC-B018-87FAFB3282A4",
      "padding": 0,
      "source": "symbol"
    },
    "com.animaapp.stc-sketch-plugin": {
      "kModelPropertiesKey": {
      }
    },
    "com.google.ux.material.spec_tools": {
      "iconStyle": "FILLED",
      "symbolName": "icon/maps/directions_railway_24px",
      "type": "icon"
    }
  },
  "verticalRulerData": {
    "_class": "rulerData",
    "base": 0,
    "do_objectID": "90D6DACC-9AE7-46BF-A5F0-C9FDA5D03FB7",
    "guides": [
    ]
  }
}