{
  "_class": "symbolMaster",
  "backgroundColor": {
    "_class": "color",
    "alpha": 1,
    "blue": 1,
    "do_objectID": "2FD91D99-89C5-4E53-A889-A1F124C861EA",
    "green": 1,
    "red": 1
  },
  "booleanOperation": 0,
  "changeIdentifier": 276,
  "clippingMaskMode": 0,
  "do_objectID": "836315B0-357A-4DA3-B336-9E62DC168057",
  "exportOptions": {
    "_class": "exportOptions",
    "do_objectID": "F784B744-1664-4BE7-A261-9B47878C31C3",
    "exportFormats": [
      {
        "_class": "exportFormat",
        "absoluteSize": 0,
        "fileFormat": "svg",
        "name": "_rounded",
        "namingScheme": 0,
        "scale": 1,
        "visibleScaleType": 0
      }
    ],
    "includedLayerIds": [
    ],
    "layerOptions": 0,
    "shouldTrim": false
  },
  "frame": {
    "_class": "rect",
    "constrainProportions": false,
    "do_objectID": "19460F46-1CCE-4C5D-975A-2EA04FC31ABC",
    "height": 24,
    "width": 24,
    "x": 1439,
    "y": 539
  },
  "hasBackgroundColor": false,
  "hasClickThrough": true,
  "hasClippingMask": false,
  "horizontalRulerData": {
    "_class": "rulerData",
    "base": 0,
    "do_objectID": "DDC8B538-BAEC-4B7A-A24B-C2C3633AF370",
    "guides": [
    ]
  },
  "includeBackgroundColorInExport": true,
  "includeBackgroundColorInInstance": true,
  "includeInCloudUpload": true,
  "isFixedToViewport": false,
  "isFlippedHorizontal": false,
  "isFlippedVertical": false,
  "isFlowHome": false,
  "isLocked": false,
  "isVisible": true,
  "layerListExpandedType": 0,
  "layers": [
    {
      "class": "shapeGroup",
      "id": "C3C51DA1-A7E1-42F5-B34F-1EF5816C6789"
    },
    {
      "class": "symbolInstance",
      "id": "916587BE-A267-4A7A-8985-F0BFEE54C24B"
    }
  ],
  "name": "icon/social/notifications_off_24px",
  "nameIsFixed": false,
  "resizesContent": false,
  "resizingConstraint": 63,
  "resizingType": 0,
  "rotation": 0,
  "shouldBreakMaskChain": true,
  "style": {
    "_class": "style",
    "do_objectID": "6004C8DE-F0B3-4E96-A87D-6E928D1E3B35",
    "endMarkerType": 0,
    "miterLimit": 10,
    "startMarkerType": 0,
    "windingRule": 1
  },
  "symbolID": "7B630BCB-1682-4CD5-95F9-EDBDF63743AD",
  "userInfo": {
    "com.amoreaux.sketch-icons": {
      "color": "51DBFA7F-7275-4C51-AD4E-19143533FEE4",
      "colorLib": "EA9A3456-D205-45BC-B018-87FAFB3282A4",
      "source": "symbol"
    },
    "com.animaapp.stc-sketch-plugin": {
      "kModelPropertiesKey": {
      }
    },
    "com.google.ux.material.spec_tools": {
      "iconStyle": "ROUNDED",
      "symbolName": "icon/social/notifications_off_24px",
      "type": "icon"
    }
  },
  "verticalRulerData": {
    "_class": "rulerData",
    "base": 0,
    "do_objectID": "B371EB6A-E835-4D94-8293-EA1F94073C4A",
    "guides": [
    ]
  }
}