{
  "_class": "symbolMaster",
  "backgroundColor": {
    "_class": "color",
    "alpha": 1,
    "blue": 1,
    "do_objectID": "3F1CE3DD-DAB7-42D2-9393-5A6421F863E9",
    "green": 1,
    "red": 1
  },
  "booleanOperation": 0,
  "changeIdentifier": 352,
  "clippingMaskMode": 0,
  "do_objectID": "26BD28CD-7CA5-478E-A2E6-029CC65C0CCA",
  "exportOptions": {
    "_class": "exportOptions",
    "do_objectID": "418ACE79-53CC-452D-A3BF-D8816C360267",
    "exportFormats": [
    ],
    "includedLayerIds": [
    ],
    "layerOptions": 0,
    "shouldTrim": false
  },
  "frame": {
    "_class": "rect",
    "constrainProportions": false,
    "do_objectID": "69006393-04A1-48F8-970E-F0CE34F72B71",
    "height": 24,
    "width": 24,
    "x": -1060,
    "y": 421
  },
  "hasBackgroundColor": false,
  "hasClickThrough": true,
  "hasClippingMask": false,
  "horizontalRulerData": {
    "_class": "rulerData",
    "base": 0,
    "do_objectID": "AAA58036-94DD-43E5-8EED-85A98CBE56D3",
    "guides": [
    ]
  },
  "includeBackgroundColorInExport": true,
  "includeBackgroundColorInInstance": true,
  "includeInCloudUpload": true,
  "isFixedToViewport": false,
  "isFlippedHorizontal": false,
  "isFlippedVertical": false,
  "isFlowHome": false,
  "isLocked": false,
  "isVisible": true,
  "layerListExpandedType": 0,
  "layers": [
    {
      "class": "shapePath",
      "id": "D67ADF4B-F7CD-4447-9CCB-560020A9291F"
    },
    {
      "class": "symbolInstance",
      "id": "B3AED95E-A4AE-4C93-9662-D249E53FF631"
    }
  ],
  "name": "icon/action/maximize_24px",
  "nameIsFixed": false,
  "resizesContent": false,
  "resizingConstraint": 63,
  "resizingType": 0,
  "rotation": 0,
  "shouldBreakMaskChain": true,
  "style": {
    "_class": "style",
    "do_objectID": "CBC5BFCF-C41A-4255-8720-CB4FC9C12DAD",
    "endMarkerType": 0,
    "miterLimit": 10,
    "startMarkerType": 0,
    "windingRule": 1
  },
  "symbolID": "193CA75A-AF57-4C83-AEC2-25A24302B9FD",
  "userInfo": {
    "com.amoreaux.sketch-icons": {
      "color": "51DBFA7F-7275-4C51-AD4E-19143533FEE4",
      "colorLib": "EA9A3456-D205-45BC-B018-87FAFB3282A4",
      "padding": 0,
      "source": "symbol"
    },
    "com.animaapp.stc-sketch-plugin": {
      "kModelPropertiesKey": {
      }
    },
    "com.google.ux.material.spec_tools": {
      "iconStyle": "FILLED",
      "symbolName": "icon/action/maximize_24px",
      "type": "icon"
    }
  },
  "verticalRulerData": {
    "_class": "rulerData",
    "base": 0,
    "do_objectID": "8D0A15E3-A3A2-4C21-9BE6-8048BDA1FE3D",
    "guides": [
    ]
  }
}