{
  "_class": "group",
  "booleanOperation": 0,
  "clippingMaskMode": 0,
  "do_objectID": "D1831E4A-889F-49FD-9104-F8A2101BAE01",
  "exportOptions": {
    "_class": "exportOptions",
    "do_objectID": "94C971E5-8725-44FF-81C0-A415ADA96565",
    "exportFormats": [
    ],
    "includedLayerIds": [
    ],
    "layerOptions": 0,
    "shouldTrim": false
  },
  "frame": {
    "_class": "rect",
    "constrainProportions": false,
    "do_objectID": "9F5B6D4C-A6C3-4F10-B331-E61660AB0034",
    "height": 3,
    "width": 5,
    "x": 13,
    "y": 7
  },
  "hasClickThrough": false,
  "hasClippingMask": false,
  "isFixedToViewport": false,
  "isFlippedHorizontal": false,
  "isFlippedVertical": false,
  "isLocked": false,
  "isVisible": true,
  "layerListExpandedType": 0,
  "layers": [
    {
      "class": "rectangle",
      "id": "2FA69EE2-73F8-4166-A570-2B005D2584D6"
    },
    {
      "class": "symbolInstance",
      "id": "3C078D02-DB9E-4228-941A-29033A988900"
    }
  ],
  "name": "↳ Dark Color",
  "nameIsFixed": false,
  "resizingConstraint": 63,
  "resizingType": 0,
  "rotation": 0,
  "shouldBreakMaskChain": false,
  "style": {
    "_class": "style",
    "do_objectID": "4EDE10D4-C5DE-498E-8642-0DD89D92B696",
    "endMarkerType": 0,
    "miterLimit": 10,
    "startMarkerType": 0,
    "windingRule": 1
  }
}