{
  "_class": "shapeGroup",
  "booleanOperation": 0,
  "clippingMaskMode": 0,
  "do_objectID": "1733B976-B59D-4AB0-A9E6-2D20BB1F2359",
  "exportOptions": {
    "_class": "exportOptions",
    "do_objectID": "19452AFC-427D-4801-B2E4-7EDD84D85CE1",
    "exportFormats": [
    ],
    "includedLayerIds": [
    ],
    "layerOptions": 0,
    "shouldTrim": false
  },
  "frame": {
    "_class": "rect",
    "constrainProportions": true,
    "do_objectID": "7E1555E3-7EE6-408A-96A3-BF9B75F1A510",
    "height": 14,
    "width": 18,
    "x": 3,
    "y": 5
  },
  "hasClickThrough": false,
  "hasClippingMask": true,
  "isFixedToViewport": false,
  "isFlippedHorizontal": false,
  "isFlippedVertical": false,
  "isLocked": false,
  "isVisible": true,
  "layerListExpandedType": 0,
  "layers": [
    {
      "class": "shapePath",
      "id": "9A85A122-B5F1-497A-8899-C11698FDE136"
    },
    {
      "class": "shapePath",
      "id": "DDEFFBCE-6A4A-456D-B699-55642A0CC392"
    }
  ],
  "name": "icon/image/crop_5_4_24px",
  "nameIsFixed": false,
  "resizingConstraint": 63,
  "resizingType": 0,
  "rotation": 0,
  "shouldBreakMaskChain": false,
  "style": {
    "_class": "style",
    "do_objectID": "CCC637B1-33D2-4A2A-9720-18076E74B4F2",
    "endMarkerType": 0,
    "fills": [
      {
        "_class": "fill",
        "color": {
          "_class": "color",
          "alpha": 1,
          "blue": 0,
          "green": 0,
          "red": 0
        },
        "fillType": 0,
        "isEnabled": false,
        "noiseIndex": 0,
        "noiseIntensity": 0,
        "patternFillType": 1,
        "patternTileScale": 1
      }
    ],
    "miterLimit": 10,
    "startMarkerType": 0,
    "windingRule": 0
  },
  "windingRule": 0
}