{
  "_class": "shapeGroup",
  "booleanOperation": 0,
  "clippingMaskMode": 0,
  "do_objectID": "AD7B37DE-4B82-4FE7-9251-2B587A948523",
  "exportOptions": {
    "_class": "exportOptions",
    "do_objectID": "A6086464-2E48-403F-B4AF-E1DF7F99427F",
    "exportFormats": [
    ],
    "includedLayerIds": [
    ],
    "layerOptions": 0,
    "shouldTrim": false
  },
  "frame": {
    "_class": "rect",
    "constrainProportions": true,
    "do_objectID": "86FBB452-2942-48BD-A091-7408FA0AC377",
    "height": 18,
    "width": 22,
    "x": 1,
    "y": 3
  },
  "hasClickThrough": false,
  "hasClippingMask": true,
  "isFixedToViewport": false,
  "isFlippedHorizontal": false,
  "isFlippedVertical": false,
  "isLocked": false,
  "isVisible": true,
  "layerListExpandedType": 0,
  "layers": [
    {
      "class": "shapePath",
      "id": "588E71EC-5847-4B86-B3B8-70B32CE174C5"
    },
    {
      "class": "shapePath",
      "id": "963A7175-3F2D-46E8-85CA-DCC8DA6D1C6B"
    },
    {
      "class": "shapePath",
      "id": "AF953983-5770-4666-8C0F-CADD9EB4EC77"
    }
  ],
  "name": "icon/av/music_video_24px",
  "nameIsFixed": false,
  "resizingConstraint": 63,
  "resizingType": 0,
  "rotation": 0,
  "shouldBreakMaskChain": false,
  "style": {
    "_class": "style",
    "do_objectID": "5BD7667E-32E4-4636-B78B-FD69714D18D5",
    "endMarkerType": 0,
    "fills": [
      {
        "_class": "fill",
        "color": {
          "_class": "color",
          "alpha": 1,
          "blue": 0,
          "green": 0,
          "red": 0
        },
        "fillType": 0,
        "isEnabled": false,
        "noiseIndex": 0,
        "noiseIntensity": 0,
        "patternFillType": 1,
        "patternTileScale": 1
      }
    ],
    "miterLimit": 10,
    "startMarkerType": 0,
    "windingRule": 0
  },
  "windingRule": 0
}