{
  "_class": "shapeGroup",
  "booleanOperation": -1,
  "clippingMaskMode": 0,
  "do_objectID": "1A27A087-FABC-4267-B501-CB40458308E3",
  "exportOptions": {
    "_class": "exportOptions",
    "exportFormats": [
    ],
    "includedLayerIds": [
    ],
    "layerOptions": 0,
    "shouldTrim": false
  },
  "frame": {
    "_class": "rect",
    "constrainProportions": false,
    "height": 17.47656258738282,
    "width": 17.48046883740234,
    "x": 3.249999956249999,
    "y": 3.261718706308594
  },
  "hasClickThrough": false,
  "hasClippingMask": true,
  "isFixedToViewport": false,
  "isFlippedHorizontal": false,
  "isFlippedVertical": false,
  "isLocked": false,
  "isVisible": true,
  "layerListExpandedType": 1,
  "layers": [
    {
      "class": "shapePath",
      "id": "F71650E9-4E59-4318-9478-75329C8F5B99"
    },
    {
      "class": "shapePath",
      "id": "B0DCE912-B12D-4064-BF62-06ABE83F3F56"
    },
    {
      "class": "shapePath",
      "id": "287A3D53-6A37-4BE0-BD3C-CDFF0EE4E301"
    },
    {
      "class": "shapePath",
      "id": "C1BD40E8-E156-4153-AA9E-4CE55A11C682"
    },
    {
      "class": "shapePath",
      "id": "147C94E3-0E49-4A25-89E5-14D51D31E742"
    },
    {
      "class": "shapePath",
      "id": "A51AE98B-FD99-45B8-BB31-EB68F2F9ECFE"
    },
    {
      "class": "shapePath",
      "id": "DD83892D-C5F9-4537-BD15-B137606EE866"
    },
    {
      "class": "shapePath",
      "id": "8302CF07-75F3-477F-B4AF-E1E491F30D16"
    },
    {
      "class": "shapePath",
      "id": "2D21F84B-D0EA-4A36-8690-06886C021D67"
    },
    {
      "class": "shapePath",
      "id": "4E4E570F-1051-4E6E-95A7-E6C9912332B5"
    },
    {
      "class": "shapePath",
      "id": "46451B11-0838-4E63-8040-04E84C8747B2"
    },
    {
      "class": "shapePath",
      "id": "1D227769-FF45-46B8-9F71-D50C651ADAD8"
    },
    {
      "class": "shapePath",
      "id": "D794B965-178F-4830-8896-3CAAB222E978"
    },
    {
      "class": "shapePath",
      "id": "ABB297E3-AA42-4028-A74E-5B5D54790159"
    },
    {
      "class": "shapePath",
      "id": "54BB0540-A1DA-4983-BAB0-2449F3553A36"
    },
    {
      "class": "shapePath",
      "id": "3B1BEBDC-A0BE-4127-AA67-733DAE6D438C"
    }
  ],
  "name": "centos",
  "nameIsFixed": false,
  "resizingConstraint": 63,
  "resizingType": 0,
  "rotation": 0,
  "shouldBreakMaskChain": false,
  "style": {
    "_class": "style",
    "endMarkerType": 0,
    "fills": [
      {
        "_class": "fill",
        "color": {
          "_class": "color",
          "alpha": 1,
          "blue": 0,
          "green": 0,
          "red": 0
        },
        "fillType": 0,
        "isEnabled": false,
        "noiseIndex": 0,
        "noiseIntensity": 0,
        "patternFillType": 1,
        "patternTileScale": 1
      }
    ],
    "miterLimit": 10,
    "startMarkerType": 0,
    "windingRule": 0
  },
  "windingRule": 0
}