{
  "_class": "shapeGroup",
  "booleanOperation": 0,
  "clippingMaskMode": 0,
  "do_objectID": "9B0A98D8-7B5D-4E2D-AE4F-9BDF83EAE3E0",
  "exportOptions": {
    "_class": "exportOptions",
    "do_objectID": "17EA95A9-3918-4345-A5EE-26CE25C5104E",
    "exportFormats": [
    ],
    "includedLayerIds": [
    ],
    "layerOptions": 0,
    "shouldTrim": false
  },
  "frame": {
    "_class": "rect",
    "constrainProportions": false,
    "do_objectID": "AC2FEC21-631B-407A-8FB1-02CB7FC5FAE3",
    "height": 18,
    "width": 18,
    "x": 3,
    "y": 3
  },
  "hasClickThrough": false,
  "hasClippingMask": true,
  "isFixedToViewport": false,
  "isFlippedHorizontal": false,
  "isFlippedVertical": false,
  "isLocked": false,
  "isVisible": true,
  "layerListExpandedType": 1,
  "layers": [
    {
      "class": "shapePath",
      "id": "B9C4AF62-0894-4574-B6EB-93881A38BDCB"
    },
    {
      "class": "shapePath",
      "id": "9FDC9839-605F-4783-A209-9EC763DEF450"
    },
    {
      "class": "shapePath",
      "id": "CB327E3F-6119-493B-BED8-B60D1055E4F8"
    }
  ],
  "name": "icon/content/unarchive_24px",
  "nameIsFixed": false,
  "resizingConstraint": 63,
  "resizingType": 0,
  "rotation": 0,
  "shouldBreakMaskChain": false,
  "style": {
    "_class": "style",
    "do_objectID": "98373EFB-5F0A-46F5-98F8-635E622831D0",
    "endMarkerType": 0,
    "fills": [
      {
        "_class": "fill",
        "color": {
          "_class": "color",
          "alpha": 1,
          "blue": 0,
          "green": 0,
          "red": 0
        },
        "fillType": 0,
        "isEnabled": false,
        "noiseIndex": 0,
        "noiseIntensity": 0,
        "patternFillType": 1,
        "patternTileScale": 1
      }
    ],
    "miterLimit": 10,
    "startMarkerType": 0,
    "windingRule": 0
  },
  "windingRule": 0
}